NOTICE
quri_parts/riqu/__init__.py
quri_parts/riqu/backend/__init__.py
quri_parts/riqu/backend/sampling.py
quri_parts/riqu/backend/sse.py
quri_parts/riqu/py.typed
quri_parts/riqu/rest/__init__.py
quri_parts/riqu/rest/api/__init__.py
quri_parts/riqu/rest/api/job_api.py
quri_parts/riqu/rest/api_client.py
quri_parts/riqu/rest/configuration.py
quri_parts/riqu/rest/models/__init__.py
quri_parts/riqu/rest/models/inline_response201.py
quri_parts/riqu/rest/models/inline_response400.py
quri_parts/riqu/rest/models/job.py
quri_parts/riqu/rest/models/jobs_body.py
quri_parts/riqu/rest/models/ssejobs_body.py
quri_parts/riqu/rest/rest.py
quri_parts_riqu-0.4.9.dist-info/LICENSE
quri_parts_riqu-0.4.9.dist-info/METADATA
quri_parts_riqu-0.4.9.dist-info/NOTICE
quri_parts_riqu-0.4.9.dist-info/WHEEL
quri_parts_riqu-0.4.9.dist-info/RECORD
