Metadata-Version: 2.1
Name: quri-parts-riqu
Version: 0.4.9
Summary: QURI Parts riqu is a support library for using quantum computers provided by the cloud server with riqu (Rest Interface for QUantum computing) interface.
Home-page: https://github.com/qiqb-osaka/quri-parts-riqu
License: Apache-2.0
Keywords: quantum,quantum computing
Author: QIQB, Osaka University
Requires-Python: >=3.9.8,<3.12
Classifier: License :: OSI Approved :: Apache Software License
Classifier: Programming Language :: Python :: 3
Classifier: Programming Language :: Python :: 3.10
Classifier: Programming Language :: Python :: 3.11
Classifier: Topic :: Scientific/Engineering :: Physics
Classifier: Typing :: Typed
Requires-Dist: certifi
Requires-Dist: quri-parts-circuit
Requires-Dist: quri-parts-core
Requires-Dist: quri-parts-openqasm (>=0.9.2)
Requires-Dist: six
Requires-Dist: typing-extensions (>=4.1.1,<5.0.0)
Requires-Dist: urllib3
Project-URL: Documentation, https://quri-parts-riqu.readthedocs.io/
Project-URL: Repository, https://github.com/qiqb-osaka/quri-parts-riqu
